[{"ref":"https://ta.igawa.blog/golang/string/","title":"文字列フォーマットの世界","section":"golang","date":"2022.12.27","body":"%#vを指定すると構造体の型名、フィールド名、値をわかりやすく表示します。\n f := \u0026amp;Foo{Bar: 1, Baz: \u0026quot;Hello, W+D Press!\u0026quot;} fmt.Printf(\u0026quot;%#v \\n\u0026quot;, f) // =\u0026gt; \u0026amp;main.Foo{Bar:1, Baz:\u0026quot;Hello, W+D Press!\u0026quot;} %vを指定すると構造体の値のみを表示します。\n f := \u0026amp;Foo{Bar: 1, Baz: \u0026quot;Hello, W+D Press!\u0026quot;} fmt.Printf(\u0026quot;%v \\n\u0026quot;, f) // =\u0026gt; \u0026amp;{1 Hello, W+D Press!} "}]